scpipelines/BarcodeFileDropest.py
scpipelines/MergeBam.py
scpipelines/ModuleBus2count.py
scpipelines/ModuleSC.py
scpipelines/ModuleVelo.py
scpipelines/__init__.py
scpipelines/cgatsc.py
scpipelines/pipeline_singlecell.py
scpipelines/pipeline_velocyto.py
scpipelines/version.py
scflow-0.0.1.dist-info/LICENCE.md
scflow-0.0.1.dist-info/METADATA
scflow-0.0.1.dist-info/WHEEL
scflow-0.0.1.dist-info/entry_points.txt
scflow-0.0.1.dist-info/top_level.txt
scflow-0.0.1.dist-info/RECORD
