Metadata-Version: 2.1
Name: scflow
Version: 0.0.1
Summary: scflow : cribbslab single cell pipeline
Home-page: UNKNOWN
Author: Adam Cribbs
Author-email: adam.cribbs@ndorms.ox.ac.uk
License: MIT
Keywords: computational genomics
Platform: any
Classifier: Development Status :: 3 - Alpha
Classifier: Intended Audience :: Science/Research
Classifier: Intended Audience :: Developers
Classifier: License :: OSI Approved
Classifier: Programming Language :: Python
Classifier: Topic :: Software Development
Classifier: Topic :: Scientific/Engineering
Classifier: Operating System :: POSIX
Classifier: Operating System :: Unix
Classifier: Operating System :: MacOS
